setup.cfg
setup.py
django_wham.egg-info/PKG-INFO
django_wham.egg-info/SOURCES.txt
django_wham.egg-info/dependency_links.txt
django_wham.egg-info/requires.txt
django_wham.egg-info/top_level.txt
wham/__init__.py
wham/admin.py
wham/fields.py
wham/httmock.py
wham/models.py
wham/tests.py
wham/views.py
wham/apis/__init__.py
wham/apis/deezer/__init__.py
wham/apis/deezer/admin.py
wham/apis/deezer/models.py
wham/apis/deezer/tests.py
wham/apis/deezer/views.py
wham/apis/eventbrite/__init__.py
wham/apis/eventbrite/admin.py
wham/apis/eventbrite/models.py
wham/apis/facebook/__init__.py
wham/apis/facebook/models.py
wham/apis/freebase/__init__.py
wham/apis/freebase/admin.py
wham/apis/freebase/models.py
wham/apis/freebase/tests.py
wham/apis/freebase/views.py
wham/apis/instagram/__init__.py
wham/apis/instagram/models.py
wham/apis/instagram/tests.py
wham/apis/lastfm/__init__.py
wham/apis/lastfm/admin.py
wham/apis/lastfm/models.py
wham/apis/lastfm/tests.py
wham/apis/lastfm/views.py
wham/apis/musicbrainz/__init__.py
wham/apis/musicbrainz/models.py
wham/apis/musicbrainz/tests.py
wham/apis/soundcloud/__init__.py
wham/apis/soundcloud/admin.py
wham/apis/soundcloud/models.py
wham/apis/soundcloud/tests.py
wham/apis/soundcloud/views.py
wham/apis/spotify/__init__.py
wham/apis/spotify/admin.py
wham/apis/spotify/models.py
wham/apis/spotify/tests.py
wham/apis/spotify/views.py
wham/apis/twitter/__init__.py
wham/apis/twitter/admin.py
wham/apis/twitter/models.py
wham/apis/twitter/tests.py
wham/apis/twitter/twitter_bearer_auth.py
wham/apis/twitter/views.py