Metadata-Version: 1.0
Name: django-wham
Version: 0.1.1
Summary: Rest APIs disguised as Django ORM Models
Home-page: https://github.com/mbylstra/django-wham
Author: Michael Bylstra
Author-email: mbylstra@gmail.com
License: UNKNOWN
Platform: UNKNOWN
